plugins/sources/__init__.py
plugins/sources/get_populartimes.py
plugins/sources/google.py
plugins/sources/icims.py
plugins/sources/mobileinsight.py
plugins/sources/newrelic.py
plugins/sources/venu.py
plugins/sources/vocinity.py
querysource/__cli__.py
querysource/__init__.py
querysource/_version.py
querysource/conf.py
querysource/connections.py
querysource/exceptions.c
querysource/exceptions.cpython-312-x86_64-linux-gnu.so
querysource/exceptions.pxd
querysource/exceptions.pyx
querysource/models.py
querysource/py.typed
querysource/services.py
querysource/version.py
querysource/cache/__init__.py
querysource/cache/base.py
querysource/cache/backends/__init__.py
querysource/cache/backends/abstract.py
querysource/cache/backends/memcache.py
querysource/cache/backends/redis.py
querysource/datasources/__init__.py
querysource/datasources/models.py
querysource/datasources/drivers/__init__.py
querysource/datasources/drivers/abstract.py
querysource/datasources/drivers/arangodb.py
querysource/datasources/drivers/athena.py
querysource/datasources/drivers/bigquery.py
querysource/datasources/drivers/cassandra.py
querysource/datasources/drivers/clickhouse.py
querysource/datasources/drivers/cockroachdb.py
querysource/datasources/drivers/couchbase.py
querysource/datasources/drivers/couchdb.py
querysource/datasources/drivers/countries.py
querysource/datasources/drivers/documentdb.py
querysource/datasources/drivers/dynamodb.py
querysource/datasources/drivers/ga.py
querysource/datasources/drivers/gcalc.py
querysource/datasources/drivers/hazel.py
querysource/datasources/drivers/influx.py
querysource/datasources/drivers/jdbc.py
querysource/datasources/drivers/jira.py
querysource/datasources/drivers/mariadb.py
querysource/datasources/drivers/memcached.py
querysource/datasources/drivers/mongo.py
querysource/datasources/drivers/mysql.py
querysource/datasources/drivers/odbc.py
querysource/datasources/drivers/openweather.py
querysource-3.17.9.dist-info/METADATA
querysource-3.17.9.dist-info/WHEEL
querysource-3.17.9.dist-info/entry_points.txt
querysource-3.17.9.dist-info/top_level.txt
querysource-3.17.9.dist-info/RECORD
querysource-3.17.9.dist-info/licenses/LICENSE
